kubectl_marimo/__init__.py
kubectl_marimo/delete.py
kubectl_marimo/deploy.py
kubectl_marimo/k8s.py
kubectl_marimo/main.py
kubectl_marimo/resources.py
kubectl_marimo/status.py
kubectl_marimo/swap.py
kubectl_marimo/sync.py
kubectl_marimo/formats/__init__.py
kubectl_marimo/formats/markdown.py
kubectl_marimo/formats/python.py
kubectl_marimo-0.2.5.dist-info/METADATA
kubectl_marimo-0.2.5.dist-info/WHEEL
kubectl_marimo-0.2.5.dist-info/entry_points.txt
kubectl_marimo-0.2.5.dist-info/licenses/LICENSE
kubectl_marimo-0.2.5.dist-info/RECORD
