Metadata-Version: 2.4
Name: kubectl-marimo
Version: 0.2.5
Summary: kubectl plugin for deploying marimo notebooks to Kubernetes
Project-URL: Homepage, https://github.com/marimo-team/marimo-operator
Project-URL: Documentation, https://github.com/marimo-team/marimo-operator/tree/main/plugin
Project-URL: Repository, https://github.com/marimo-team/marimo-operator
Project-URL: Issues, https://github.com/marimo-team/marimo-operator/issues
Author: marimo-team
License: Apache-2.0
License-File: LICENSE
Keywords: kubectl,kubernetes,marimo,notebook,plugin
Classifier: Development Status :: 4 - Beta
Classifier: Environment :: Console
Classifier: Intended Audience :: Developers
Classifier: License :: OSI Approved :: Apache Software License
Classifier: Operating System :: OS Independent
Classifier: Programming Language :: Python :: 3
Classifier: Programming Language :: Python :: 3.10
Classifier: Programming Language :: Python :: 3.11
Classifier: Programming Language :: Python :: 3.12
Classifier: Topic :: Software Development
Requires-Python: >=3.10
Requires-Dist: click>=8.0
Requires-Dist: kubernetes>=28.0
Requires-Dist: pyyaml>=6.0
Provides-Extra: dev
Requires-Dist: pytest-mock>=3.0; extra == 'dev'
Requires-Dist: pytest>=7.0; extra == 'dev'
Requires-Dist: ty>=0.0.1a6; extra == 'dev'
